b_aws_s3_backup/__init__.py
b_aws_s3_backup/color_print.py
b_aws_s3_backup/print_colors.py
b_aws_s3_backup/cli_actions/__init__.py
b_aws_s3_backup/cli_actions/backup.py
b_aws_s3_backup/cli_actions/base_cli_actions.py
b_aws_s3_backup/cli_actions/restore.py
b_aws_s3_backup/cli_actions/seed.py
b_aws_s3_backup/exceptions/__init__.py
b_aws_s3_backup/exceptions/backup_not_found.py
b_aws_s3_backup/exceptions/s3_bucket_not_found.py
b_aws_s3_backup/s3_actions/__init__.py
b_aws_s3_backup/s3_actions/base_s3_action.py
b_aws_s3_backup/s3_actions/download_s3_bucket.py
b_aws_s3_backup/s3_actions/seed_s3_bucket.py
b_aws_s3_backup/s3_actions/upload_s3.py
b_aws_s3_backup-1.0.0.dist-info/LICENSE
b_aws_s3_backup-1.0.0.dist-info/METADATA
b_aws_s3_backup-1.0.0.dist-info/WHEEL
b_aws_s3_backup-1.0.0.dist-info/entry_points.txt
b_aws_s3_backup-1.0.0.dist-info/top_level.txt
b_aws_s3_backup-1.0.0.dist-info/RECORD
