Metadata-Version: 2.1
Name: b-aws-s3-backup
Version: 1.0.0
Summary: S3.
Home-page: https://github.com/biomapas/B.AwsS3Backup.git
Author: Laimonas Sutkus
Author-email: laimonas.sutkus@biomapas.com
License: Apache License 2.0
Keywords: S3
Platform: UNKNOWN
Requires-Dist: boto3
Requires-Dist: b-continuous-subprocess (<1.0.0,>=0.3.2)
